{
  "success": true,
  "language_code": "guj",
  "language_label": "ગુજરાતી",
  "topics_text": "1. પ્રાસ્તાવિક  \n- અખિલાની ચકડોળમાં બેસવાની સંખ્યાને x અને હૂપલા રમવાની સંખ્યાને y કહો. આ પરિસ્થિતિને બે સમીકરણો દ્વારા દર્શાવી શકાય: 3x + 4y = 20 અને x = 2y. આ ઉદાહરણ દ્વારા દ્વિચલ સુરેખ સમીકરણયુગ્મની ઉકેલની વિવિધ રીતોનું અભ્યાસ કરાશે.  \n\n2. આલેખની રીત  \n- રેખાઓનું નિરૂપણ અને ઉકેલના અસ્તિત્વ વિશે નીચે મુજબ કહી શકાય: (i) રેખાઓ 2 સમીકરણો જોડ છે અને એક અનન્ય ઉકેલ (સુસંગત) છે; (ii) રેખાઓ સંપાતી છે અને એક અનન્ય ઉકેલ (સુસંગત) છે; (iii) રેખાઓ સમાંતર છે અને કોઈ સામાન્ય ઉકેલ (અસુસંગત) નથી.  \n- કોષ્ટક 3.1 માં વિવિધ પ્રકારની રેખાઓ (અનન્ય, અનંત, કોઈ ઉકેલ ન હોય) અને તેમની સહગુણકોનું વર્ણન છે, જેમ કે x – 2y = 0 અને 3x + 4y – 20 = 0 એક અનન્ય ઉકેલ દેખાડે છે, 2x + 3y – 9 = 0 અને 4x + 6y – 18 = 0 સંપાતી રેખાઓ છે, 2x + 4y – 12 = 0 સમાંતર રેખાઓ છે અને ઉકેલ નથી.  \n- ઉદાહરણ 1 માં y = 2x – 4 અને x – 2y = 0 ની આલેખ દોરીને બિંદુ A(0,2), B(6,0), P(0,–4), Q(–2,0) જોડતી AB અને PQ રેખાઓ દેખાડવામાં આવી, અને સામાન્ય બિંદુ (6,0) માટે x = 6, y = 0 મળ્યું, એટલે સમીકરણયુગ્મ સુસંગત છે.  \n- ઉદાહરણ 2 માં 5x – 8y + 10 = 0 અને 2x – 3y + 5 = 0 સમીકરણો સંપાતી રેખાઓ છે, તેથી અનંત ઉકેલ મળે છે.  \n- ઉદાહરણ 3 માં પેન્ટ અને સ્કર્ટ ખરીદવાની સમસ્યા x અને y ચલોથી 2x – y = 4 અને 4x – y = 8 સમીકરણો માટે આલેખ દોરવામાં આવી, અને x = 1, y = 0 મળ્યું, એટલે 1 પેન્ટ ખરીદવામાં આવે છે અને સ્કર્ટ નથી.  \n\n3. સુરેખ સમીકરણયુગ્મનો ઉકેલ મેળવવાની બેજિક રીત  \n- આ વિભાગમાં આદેશની (સબ્સ્ટિટ્યુશન) અને લોપની (એલિમિનેશન) વધુ બૈજિક પદ્ધતિઓ વિશે ચર્ચા કરવામાં આવશે, જે આલેખ પદ્ધતિ થી અનુકૂળ ન હોતી પરિસ્થિતિઓમાં ઉપયોગી છે.  \n\n   3.1 આદેશની રીત  \n   - આ પદ્ધતિમાં એક સમીકરણ માંથી એક ચલને બીજા ચલના સ્વરૂપમાં મળાવી લેવામાં આવે છે, જેમ કે x = 3 – 2y (સમીકરણ 2 માંથી). પછી આ મૂલ્યને બીજા સમીકરણ માં મૂકી એક ચલ વાળા સમીકરણ મળે છે અને તે ઉકેલવામાં આવે છે. ઉદાહરણ 4 માં x + 2y – 3 = 0 માટે x = 3 – 2y મળી, તે મૂલ્યને સમીકરણ 1 માં મૂકી y = 2 મળ્યું અને x = –1 મળ્યું.  \n   - ઉદાહરણ 5 માં આફતાબ અને પુત્રીની ઉંમરની સમસ્યા સબ્સ્ટિટ્યુશન થી ઉકેલવામાં આવી છે, જેમાં x = 42 વર્ષ અને y = 12 વર્ષ મળ્યા.  \n   - ઉદાહરણ 6 માં 2 પેન્સિલ + 3 રબર = 9 અને 4 પેન્સિલ + 6 રબર = 18 સમીકરણો સમાન છે, અથવા અનંત ઉકેલ મળ્યો અને એક પેન્સિલ અને એક રબર ની અનન્ય કિંમત નક્કી નથઈ શકે.  \n   - ઉદાહરણ 7 માં રેલવે પાટાઓ ની સમીકરણો સંપાતી નથી અને કોઈ સામાન્ય ઉકેલ નથી, અથવા પાટાઓ એકબીજાને છેદતા નથી.  \n\n   3.2 લોપની રીત  \n   - આ પદ્ધતિમાં બંને સમીકરણોના એક ચલના સહગુણકો સમાન કરવા માટે સંખ્યાઓ થી ગુણવામાં આવે છે, પછી એક સમીકરણ માં બીજું સમીકરણ જોડીને એક ચલ લોપ કરી દેવામાં આવે છે. જો લોપ પછી સાચો સમીકરણ મળે તો ઉકેલ મળે છે; જો અસત્ય વિવરણ મળે તો કોઈ ઉકેલ નથી; જો ચલ વિનાનું સત્ય વિવરણ મળે તો અનંત ઉકેલ છે.  \n   - ઉદાહરણ 8 માં માસિક આવક અને ખર્ચ નું સંબંધ લોપ પદ્ધતિ થી મળી છે, જેમાં x = 2000, y = 4000 મળી અને આવક ₹ 18,000 અને ₹ 14,000 મળી.  \n   - ઉદાહરણ 9 માં 2x + 3y = 0 અને 4x + 6y = 0 સમીકરણો લોપ પછી 0 = 9 મળ્યું જે અસત્ય છે, અથવા સમીકરણયુગ્મ ને ઉકેલ નથી.  \n   - ઉદાહરણ 10 માં બે અંકની સંખ્યા અને તેની અદલાબદલી સંખ્યા નો સંયોજન લોપ પદ્ધતિ થી મળી છે, જેમાં x = 4, y = 2 મળી અને સંખ્યા 42 મળે છે; બીજી સંભવિત સંયોજન માં x = 2, y = 4 મળી અને સંખ્યા 24 મળે છે, અથવા બે સંખ્યો 42 અને 24 મળે છે.  \n\n4. સ્વાધ્યાય 3.1 (પ્રશ્નો)  \n- “ધોરણ X K ના દસ વિદ્યાર્થીઓ ગણિત કોયડાની સ્પર્ધામાં ભાગ લે છે…”, “5 પેન્સિલ અને 7 પેન ની કુલ કિંમત ₹ 50 છે…”, “નીચેના સુરેખ સમીકરણયુગ્મ થી બનતી રેખાઓ એક બિંદુમાં છેદે છે કે સમાંતર છે કે સંપાતી છે…”, “સુરેખ સમીકરણ 2x + 3y – 8 = 0 આપેલ છે અને બીજું સમીકરણ લખો જે (i) છેદતી (ii) સમાંતર (iii) સંપાતી રેખાઓ દેખાડે છે”, “સુરેખ સમીકરણો 7x – 1 = 0 અને 3x + 2y – 12 = 0 દ્વારા રેખાઓ નું આલેખ દોરો અને ત્રિકોણ બનાવો” આવા પ્રશ્નો માટે સમીકરણયુગ્મ બનાવી અને આલેખ પદ્ધતિ થી ઉકેલ મળવો.  \n\n5. સ્વાધ્યાય 3.2 (આદેશની પદ્ધતિ પ્રશ્નો)  \n- “2x + 3y = 11 અને 2x – 4y = –24 નો ઉકેલ મળો અને એવો m ખોજો કે y = mx + 3 હોય”, “બે સંખ્યાનો તફાવત 26 છે અને એક સંખ્યા બીજા સંખ્યા થી ત્રણ ગણી છે તો સંખ્યો મળો”, “બે પૂરક કોણો મોટો ખૂણો નાના ખૂણાથી 18° મોટો છે તો પૂરક કોણો મળો”, “ક્રિકેટ ટીમ એ 7 બેટ અને 6 ડેડા ₹ 3800 માં ખરીદ્યા અને પછી 3 બેટ અને 5 ડેડા ₹ 1750 માં ખરીદ્યા તો એક બેટ અને એક ડેડાની કિંમત મળો”, “ટૅક્સી ભાડું નિશ્ચિત અને પ્રતિ કિમી દર માટે મળો અને 25 કિમી માટે કેટલું ભાડું ચૂકવવું છે”, “અપૂર્ણાંક ની અંશ અને છેદ બંનેમાં 2 ઉમેરો તો 1 મળે છે અને 3 ઉમેરો તો –1 મળે છે તો અપૂર્ણાંક મળો”, “પાંચ વર્ષ પછી જેકબ ની ઉંમર પુત્ર ની ઉંમર થી ત્રણ ગણી હશે અને પાંચ વર્ષ પહેલાં જેકબ ની ઉંમર સાત ગણી હતી તો વર્તમાન ઉંમર મળો”.  \n\n6. સ્વાધ્યાય 3.3 (લોપની પદ્ધતિ પ્રશ્નો)  \n- “સમીકરણ x – 7 = 5 અને 2x – 3 = 4 માટે લોપ અને આદેશ પદ્ધતિ થી ઉકેલ મળો”, “3x + 4y = 10 અને 2x – 2y = 5 માટે લોપ પદ્ધતિ થી ઉકેલ મળો”, “3x – 5y – 4 = 0 અને 9x = 2y + 7 માટે લોપ પદ્ધતિ થી ઉકેલ મળો”, “એક અપૂર્ણાંક ની અંશ માં 1 ઉમેરો અને છેદ માંથી 1 બાદ કરો તો અપૂર્ણાંક નું અતિસંક્ષિપ્ત રૂપ 1 મળે છે; માત્ર છેદ માં 1 ઉમેરો તો અતિસંક્ષિપ્ત રૂપ –1 મળે છે તો અપૂર્ણાંક મળો”.  \n\n(પ્રત્યેક વિષય અને ઉપવિષય માં મૂળ પાઠ્યપુસ્તક ની વાક્યો જિતલા સંભવ તેટલા ઉપયોગ કરવામાં આવ્યાં છે, પેજ નંબર અથવા ફૂટર ટેક્સ્ટ નથી સમાવેશ કરવામાં આવ્યું.)",
  "headings": [
    [
      "3.1",
      "આદેશની રીત"
    ],
    [
      "3.2",
      "લોપની રીત"
    ]
  ],
  "chapter_titles": [
    "આદેશની રીત",
    "લોપની રીત",
    "પ્રાસ્તાવિક",
    "(aaa સુરેખ સમીકરણયુગ્મના ઉકેલ માટે આલેખની રીત re",
    "GL ४1",
    "આકૃતિ 3.1",
    "3 _",
    "સુરેખ સમીકરણયુગ્મનો ઉકેલ મેળવાની બેજિક રીત",
    "1) .. તૃ - - ડી",
    "આદેશની રીત : કેટલાંક ઉદાહરણોની મદદથી આપણે આદેશની રીતની ચર્ચા કરીશું",
    "6/+ 69 = 18",
    "| ગુણોત્તર 4:3 છે. જો દરેક વ્યક્તિ માસિક ₹ 2000 ની બચત કરે, તો તેમની માસિક આવક શોધો"
  ],
  "chapter_title": "આદેશની રીત",
  "excerpt": "na\n\nHee) [Baa સુરેખ સમીકરણયુગ્મ| 3\n\n3.1 પ્રાસ્તાવિક\n\nતમે નીચે આપેલી પરિસ્થિતિ જેવી પરિસ્થિતિમાંથી પસાર થયાં જ હશો.\nઅખિલા તેના ગામમાં મેળામાં ગઈ હતી. તેને ચકડોળમાં બેસવાનો આનંદ માણવો હતો અને હૂપલા (Hoopla)\n(જેમાં તમે સ્ટોલમાં રાખેલી વસ્તુઓ પર રિંગ ફેંકો અને જો રિંગ કોઈ પણ વસ્તુને સંપૂર્ણ આવરી લે, તો તે વસ્તુ\nતમને મળે એવી એક રમત) રમવા માંગતી હતી. તે જેટલી વખત Guat રમી તે સંખ્યા એ ચકડોળ પરની સવારીની\nસંખ્યાથી અડધી છે. જો પ્રત્યેક વખત ચકડોળમાં બેસવાનો ખર્ચ ₹ 3 અને હૂપલાની પ્રત્યેક રમત રમવાનો ખર્ચ ₹ 4\nથતો હોય, તો તમે ચકડોળમાં બેસવાની સંખ્યા કેવી રીતે શોધી શકશો અને તે કેટલી વાર હૂપલાની રમત રમી હશે ते\nકેવી રીતે નક્કી કરશો? તેણે આ માટે કુલ ₹ 20 ખર્ચ્યા હતા.\n\nકદાચિત્‌, તમે વિવિધ સ્થિતિની વિચારણા કરીને અજમાવી શકો છો. જો તેણે એક વખત સવારી કરી હોય, ते\nશક્ય છે ? શું બે વખત સવારી શક્ય છે ? અને આમ આગળ ચાલો અથવા આવી પરિસ્થિતિઓને દર્શાવવા માટે તમે\nધોરણ IX ના દ્વિચલ સુરેખ સમીકરણોના જ્ઞાનનો ઉપયોગ કરી શકો.\n\n\fગણિત\n\nચાલો આ અભિગમ અપનાવીએ.\nઅખિલાની ચકડોળમાં બેસવાની સંખ્યાને x કહો અને Cua રમવાની સંખ્યાને 9 કહો. ",
  "topics": [
    {
      "title": "પ્રાસ્તાવિક",
      "summary": "",
      "subtopics": [
        {
          "title": "અખિલાની ચકડોળમાં બેસવાની સંખ્યાને x અને હૂપલા રમવાની સંખ્યાને y કહો. આ પરિસ્થિતિને બે સમીકરણો દ્વારા દર્શાવી શકાય",
          "narration": "3x + 4y = 20 અને x = 2y. આ ઉદાહરણ દ્વારા દ્વિચલ સુરેખ સમીકરણયુગ્મની ઉકેલની વિવિધ રીતોનું અભ્યાસ કરાશે."
        }
      ],
      "topic_id": "1"
    },
    {
      "title": "આલેખની રીત",
      "summary": "",
      "subtopics": [
        {
          "title": "રેખાઓનું નિરૂપણ અને ઉકેલના અસ્તિત્વ વિશે નીચે મુજબ કહી શકાય",
          "narration": "(i) રેખાઓ 2 સમીકરણો જોડ છે અને એક અનન્ય ઉકેલ (સુસંગત) છે; (ii) રેખાઓ સંપાતી છે અને એક અનન્ય ઉકેલ (સુસંગત) છે; (iii) રેખાઓ સમાંતર છે અને કોઈ સામાન્ય ઉકેલ (અસુસંગત) નથી."
        },
        {
          "title": "કોષ્ટક 3.1 માં વિવિધ પ્રકારની રેખાઓ (અનન્ય, અનંત, કોઈ ઉકેલ ન હોય) અને તેમની સહગુણકોનું વર્ણન છે, જેમ કે x – 2y = 0 અને 3x + 4y – 20 = 0 એક અનન્ય ઉકેલ દેખાડે છે, 2x + 3y – 9 = 0 અને 4x + 6y – 18 = 0 સંપાતી રેખાઓ છે, 2x + 4y – 12 = 0 સમાંતર રેખાઓ છે અને ઉકેલ નથી.",
          "narration": ""
        },
        {
          "title": "ઉદાહરણ 1 માં y = 2x – 4 અને x – 2y = 0 ની આલેખ દોરીને બિંદુ A(0,2), B(6,0), P(0,–4), Q(–2,0) જોડતી AB અને PQ રેખાઓ દેખાડવામાં આવી, અને સામાન્ય બિંદુ (6,0) માટે x = 6, y = 0 મળ્યું, એટલે સમીકરણયુગ્મ સુસંગત છે.",
          "narration": ""
        },
        {
          "title": "ઉદાહરણ 2 માં 5x – 8y + 10 = 0 અને 2x – 3y + 5 = 0 સમીકરણો સંપાતી રેખાઓ છે, તેથી અનંત ઉકેલ મળે છે.",
          "narration": ""
        },
        {
          "title": "ઉદાહરણ 3 માં પેન્ટ અને સ્કર્ટ ખરીદવાની સમસ્યા x અને y ચલોથી 2x – y = 4 અને 4x – y = 8 સમીકરણો માટે આલેખ દોરવામાં આવી, અને x = 1, y = 0 મળ્યું, એટલે 1 પેન્ટ ખરીદવામાં આવે છે અને સ્કર્ટ નથી.",
          "narration": ""
        }
      ],
      "topic_id": "2"
    },
    {
      "title": "સુરેખ સમીકરણયુગ્મનો ઉકેલ મેળવવાની બેજિક રીત",
      "summary": "",
      "subtopics": [
        {
          "title": "આ વિભાગમાં આદેશની (સબ્સ્ટિટ્યુશન) અને લોપની (એલિમિનેશન) વધુ બૈજિક પદ્ધતિઓ વિશે ચર્ચા કરવામાં આવશે, જે આલેખ પદ્ધતિ થી અનુકૂળ ન હોતી પરિસ્થિતિઓમાં ઉપયોગી છે.",
          "narration": ""
        }
      ],
      "topic_id": "3"
    },
    {
      "title": "1 આદેશની રીત",
      "summary": "",
      "subtopics": [
        {
          "title": "આ પદ્ધતિમાં એક સમીકરણ માંથી એક ચલને બીજા ચલના સ્વરૂપમાં મળાવી લેવામાં આવે છે, જેમ કે x = 3 – 2y (સમીકરણ 2 માંથી). પછી આ મૂલ્યને બીજા સમીકરણ માં મૂકી એક ચલ વાળા સમીકરણ મળે છે અને તે ઉકેલવામાં આવે છે. ઉદાહરણ 4 માં x + 2y – 3 = 0 માટે x = 3 – 2y મળી, તે મૂલ્યને સમીકરણ 1 માં મૂકી y = 2 મળ્યું અને x = –1 મળ્યું.",
          "narration": ""
        },
        {
          "title": "ઉદાહરણ 5 માં આફતાબ અને પુત્રીની ઉંમરની સમસ્યા સબ્સ્ટિટ્યુશન થી ઉકેલવામાં આવી છે, જેમાં x = 42 વર્ષ અને y = 12 વર્ષ મળ્યા.",
          "narration": ""
        },
        {
          "title": "ઉદાહરણ 6 માં 2 પેન્સિલ + 3 રબર = 9 અને 4 પેન્સિલ + 6 રબર = 18 સમીકરણો સમાન છે, અથવા અનંત ઉકેલ મળ્યો અને એક પેન્સિલ અને એક રબર ની અનન્ય કિંમત નક્કી નથઈ શકે.",
          "narration": ""
        },
        {
          "title": "ઉદાહરણ 7 માં રેલવે પાટાઓ ની સમીકરણો સંપાતી નથી અને કોઈ સામાન્ય ઉકેલ નથી, અથવા પાટાઓ એકબીજાને છેદતા નથી.",
          "narration": ""
        }
      ],
      "topic_id": "4"
    },
    {
      "title": "2 લોપની રીત",
      "summary": "",
      "subtopics": [
        {
          "title": "આ પદ્ધતિમાં બંને સમીકરણોના એક ચલના સહગુણકો સમાન કરવા માટે સંખ્યાઓ થી ગુણવામાં આવે છે, પછી એક સમીકરણ માં બીજું સમીકરણ જોડીને એક ચલ લોપ કરી દેવામાં આવે છે. જો લોપ પછી સાચો સમીકરણ મળે તો ઉકેલ મળે છે; જો અસત્ય વિવરણ મળે તો કોઈ ઉકેલ નથી; જો ચલ વિનાનું સત્ય વિવરણ મળે તો અનંત ઉકેલ છે.",
          "narration": ""
        },
        {
          "title": "ઉદાહરણ 8 માં માસિક આવક અને ખર્ચ નું સંબંધ લોપ પદ્ધતિ થી મળી છે, જેમાં x = 2000, y = 4000 મળી અને આવક ₹ 18,000 અને ₹ 14,000 મળી.",
          "narration": ""
        },
        {
          "title": "ઉદાહરણ 9 માં 2x + 3y = 0 અને 4x + 6y = 0 સમીકરણો લોપ પછી 0 = 9 મળ્યું જે અસત્ય છે, અથવા સમીકરણયુગ્મ ને ઉકેલ નથી.",
          "narration": ""
        },
        {
          "title": "ઉદાહરણ 10 માં બે અંકની સંખ્યા અને તેની અદલાબદલી સંખ્યા નો સંયોજન લોપ પદ્ધતિ થી મળી છે, જેમાં x = 4, y = 2 મળી અને સંખ્યા 42 મળે છે; બીજી સંભવિત સંયોજન માં x = 2, y = 4 મળી અને સંખ્યા 24 મળે છે, અથવા બે સંખ્યો 42 અને 24 મળે છે.",
          "narration": ""
        }
      ],
      "topic_id": "5"
    },
    {
      "title": "સ્વાધ્યાય 3.1 (પ્રશ્નો)",
      "summary": "",
      "subtopics": [
        {
          "title": "“ધોરણ X K ના દસ વિદ્યાર્થીઓ ગણિત કોયડાની સ્પર્ધામાં ભાગ લે છે…”, “5 પેન્સિલ અને 7 પેન ની કુલ કિંમત ₹ 50 છે…”, “નીચેના સુરેખ સમીકરણયુગ્મ થી બનતી રેખાઓ એક બિંદુમાં છેદે છે કે સમાંતર છે કે સંપાતી છે…”, “સુરેખ સમીકરણ 2x + 3y – 8 = 0 આપેલ છે અને બીજું સમીકરણ લખો જે (i) છેદતી (ii) સમાંતર (iii) સંપાતી રેખાઓ દેખાડે છે”, “સુરેખ સમીકરણો 7x – 1 = 0 અને 3x + 2y – 12 = 0 દ્વારા રેખાઓ નું આલેખ દોરો અને ત્રિકોણ બનાવો” આવા પ્રશ્નો માટે સમીકરણયુગ્મ બનાવી અને આલેખ પદ્ધતિ થી ઉકેલ મળવો.",
          "narration": ""
        }
      ],
      "topic_id": "6"
    },
    {
      "title": "સ્વાધ્યાય 3.2 (આદેશની પદ્ધતિ પ્રશ્નો)",
      "summary": "",
      "subtopics": [
        {
          "title": "“2x + 3y = 11 અને 2x – 4y = –24 નો ઉકેલ મળો અને એવો m ખોજો કે y = mx + 3 હોય”, “બે સંખ્યાનો તફાવત 26 છે અને એક સંખ્યા બીજા સંખ્યા થી ત્રણ ગણી છે તો સંખ્યો મળો”, “બે પૂરક કોણો મોટો ખૂણો નાના ખૂણાથી 18° મોટો છે તો પૂરક કોણો મળો”, “ક્રિકેટ ટીમ એ 7 બેટ અને 6 ડેડા ₹ 3800 માં ખરીદ્યા અને પછી 3 બેટ અને 5 ડેડા ₹ 1750 માં ખરીદ્યા તો એક બેટ અને એક ડેડાની કિંમત મળો”, “ટૅક્સી ભાડું નિશ્ચિત અને પ્રતિ કિમી દર માટે મળો અને 25 કિમી માટે કેટલું ભાડું ચૂકવવું છે”, “અપૂર્ણાંક ની અંશ અને છેદ બંનેમાં 2 ઉમેરો તો 1 મળે છે અને 3 ઉમેરો તો –1 મળે છે તો અપૂર્ણાંક મળો”, “પાંચ વર્ષ પછી જેકબ ની ઉંમર પુત્ર ની ઉંમર થી ત્રણ ગણી હશે અને પાંચ વર્ષ પહેલાં જેકબ ની ઉંમર સાત ગણી હતી તો વર્તમાન ઉંમર મળો”.",
          "narration": ""
        }
      ],
      "topic_id": "7"
    },
    {
      "title": "સ્વાધ્યાય 3.3 (લોપની પદ્ધતિ પ્રશ્નો)",
      "summary": "(પ્રત્યેક વિષય અને ઉપવિષય માં મૂળ પાઠ્યપુસ્તક ની વાક્યો જિતલા સંભવ તેટલા ઉપયોગ કરવામાં આવ્યાં છે, પેજ નંબર અથવા ફૂટર ટેક્સ્ટ નથી સમાવેશ કરવામાં આવ્યું.)",
      "subtopics": [
        {
          "title": "“સમીકરણ x – 7 = 5 અને 2x – 3 = 4 માટે લોપ અને આદેશ પદ્ધતિ થી ઉકેલ મળો”, “3x + 4y = 10 અને 2x – 2y = 5 માટે લોપ પદ્ધતિ થી ઉકેલ મળો”, “3x – 5y – 4 = 0 અને 9x = 2y + 7 માટે લોપ પદ્ધતિ થી ઉકેલ મળો”, “એક અપૂર્ણાંક ની અંશ માં 1 ઉમેરો અને છેદ માંથી 1 બાદ કરો તો અપૂર્ણાંક નું અતિસંક્ષિપ્ત રૂપ 1 મળે છે; માત્ર છેદ માં 1 ઉમેરો તો અતિસંક્ષિપ્ત રૂપ –1 મળે છે તો અપૂર્ણાંક મળો”.",
          "narration": ""
        }
      ],
      "topic_id": "8"
    }
  ]
}